{
	"info": {
		"_postman_id": "38dc4bf4-275e-46f5-8165-483af57b90c2",
		"name": "endereço-api",
		"schema": "https://schema.getpostman.com/json/collection/v2.1.0/collection.json",
		"_exporter_id": "17081315"
	},
	"item": [
		{
			"name": "cidade",
			"item": [
				{
					"name": "listagem",
					"request": {
						"method": "GET",
						"header": [
							{
								"key": "Accept",
								"value": "application/json",
								"type": "text"
							}
						],
						"url": {
							"raw": "http://127.0.0.1:8000/api/cidade/listagem",
							"protocol": "http",
							"host": [
								"127",
								"0",
								"0",
								"1"
							],
							"port": "8000",
							"path": [
								"api",
								"cidade",
								"listagem"
							]
						}
					},
					"response": []
				}
			]
		},
		{
			"name": "endereço",
			"item": [
				{
					"name": "criar",
					"request": {
						"method": "POST",
						"header": [
							{
								"key": "Accept",
								"value": "application/json",
								"type": "text"
							}
						],
						"body": {
							"mode": "formdata",
							"formdata": [
								{
									"key": "logradouro",
									"value": "Rua de Tal 2",
									"type": "text"
								},
								{
									"key": "numero",
									"value": "182",
									"type": "text"
								},
								{
									"key": "bairro",
									"value": "Bairro de tall",
									"type": "text"
								},
								{
									"key": "cidade_id",
									"value": "3300100",
									"type": "text"
								}
							]
						},
						"url": {
							"raw": "http://127.0.0.1:8000/api/endereco/criar",
							"protocol": "http",
							"host": [
								"127",
								"0",
								"0",
								"1"
							],
							"port": "8000",
							"path": [
								"api",
								"endereco",
								"criar"
							]
						}
					},
					"response": []
				},
				{
					"name": "listagem",
					"request": {
						"method": "GET",
						"header": [
							{
								"key": "Accept",
								"value": "application/json",
								"type": "text"
							}
						],
						"url": {
							"raw": "http://127.0.0.1:8000/api/endereco/listagem",
							"protocol": "http",
							"host": [
								"127",
								"0",
								"0",
								"1"
							],
							"port": "8000",
							"path": [
								"api",
								"endereco",
								"listagem"
							]
						}
					},
					"response": []
				},
				{
					"name": "atualizar",
					"request": {
						"method": "POST",
						"header": [
							{
								"key": "Accept",
								"value": "application/json",
								"type": "text"
							}
						],
						"body": {
							"mode": "formdata",
							"formdata": [
								{
									"key": "bairro",
									"value": "Bairro de tal 2",
									"type": "text"
								},
								{
									"key": "logradouro",
									"value": "Rua de tal 2",
									"type": "text"
								},
								{
									"key": "numero",
									"value": "22",
									"type": "text"
								},
								{
									"key": "cidade_id",
									"value": "3300308",
									"type": "text"
								}
							]
						},
						"url": {
							"raw": "http://127.0.0.1:8000/api/endereco/30/atualizar",
							"protocol": "http",
							"host": [
								"127",
								"0",
								"0",
								"1"
							],
							"port": "8000",
							"path": [
								"api",
								"endereco",
								"30",
								"atualizar"
							]
						}
					},
					"response": []
				},
				{
					"name": "New Request",
					"request": {
						"method": "DELETE",
						"header": [
							{
								"key": "Accept",
								"value": "application/json",
								"type": "text"
							}
						],
						"url": {
							"raw": "http://127.0.0.1:8000/api/endereco/30/deletar",
							"protocol": "http",
							"host": [
								"127",
								"0",
								"0",
								"1"
							],
							"port": "8000",
							"path": [
								"api",
								"endereco",
								"30",
								"deletar"
							]
						}
					},
					"response": []
				}
			]
		}
	]
}